django_alacarte-0.1.6.dist-info/top_level.txt
django_alacarte-0.1.6.dist-info/metadata.json
django_alacarte-0.1.6.dist-info/RECORD
django_alacarte-0.1.6.dist-info/METADATA
django_alacarte-0.1.6.dist-info/DESCRIPTION.rst
django_alacarte-0.1.6.dist-info/WHEEL
alacarte/__init__.py
alacarte/tests.py
alacarte/apps.py
alacarte/menus.py
alacarte/templates/alacarte/menu.html
alacarte/templatetags/__init__.py
alacarte/templatetags/alacarte.py
