Metadata-Version: 2.0
Name: django-alacarte
Version: 0.1.6
Summary: A minimalist Django menu app.
Home-page: https://github.com/mstrcnvs/django-alacarte
Author: Rafael Canovas
Author-email: rafaelcanovas@me.com
License: UNKNOWN
Platform: UNKNOWN
Classifier: Development Status :: 3 - Alpha
Classifier: Environment :: Web Environment
Classifier: Framework :: Django
Classifier: Intended Audience :: Developers
Classifier: Intended Audience :: Developers
Classifier: Programming Language :: Python :: 2.7
Classifier: Programming Language :: Python :: 3
Classifier: Programming Language :: Python :: 3.3
Classifier: Topic :: Software Development :: Libraries :: Python Modules
Classifier: Topic :: Utilities
Requires-Dist: Django
